MANIFEST.in
README.rst
requirements.txt
setup.py
auto_argcomplete/__init__.py
auto_argcomplete/__version__.py
auto_argcomplete/cli.py
auto_argcomplete/utils.py
auto_argcomplete.egg-info/PKG-INFO
auto_argcomplete.egg-info/SOURCES.txt
auto_argcomplete.egg-info/dependency_links.txt
auto_argcomplete.egg-info/entry_points.txt
auto_argcomplete.egg-info/pbr.json
auto_argcomplete.egg-info/requires.txt
auto_argcomplete.egg-info/top_level.txt
auto_argcomplete/packages/__init__.py
auto_argcomplete/packages/docopt.py
auto_argcomplete/tests/__init__.py
auto_argcomplete/tests/test_cli.py
completion/_auto_argcomplete
completion/auto_argcomplete-completion.bash